{"Logs":[{"time":"2025-08-21T17:36:01.9203407+04:00","message":"log"},{"time":"2025-08-21T17:36:06.4782591+04:00","message":"list"},{"time":"2025-08-21T17:36:06.4782591+04:00","message":"📅Cписок событий✅"},{"time":"2025-08-21T17:36:06.4782591+04:00","message":"событий нет"},{"time":"2025-08-21T17:36:12.29195+04:00","message":"log"},{"time":"2025-08-21T17:36:39.458623+04:00","message":"add \"тест\" \"2025-12-12\" \"high\""},{"time":"2025-08-21T17:36:39.458623+04:00","message":"Событие: тест добавлено"}],"Storage":{}}